_nebari/__init__.py
_nebari/_version.py
_nebari/cli.py
_nebari/config.py
_nebari/config_set.py
_nebari/constants.py
_nebari/deploy.py
_nebari/deprecate.py
_nebari/destroy.py
_nebari/initialize.py
_nebari/keycloak.py
_nebari/render.py
_nebari/upgrade.py
_nebari/utils.py
_nebari/version.py
_nebari/provider/__init__.py
_nebari/provider/git.py
_nebari/provider/helm.py
_nebari/provider/kubernetes.py
_nebari/provider/kustomize.py
_nebari/provider/opentofu.py
_nebari/provider/cicd/__init__.py
_nebari/provider/cicd/common.py
_nebari/provider/cicd/github.py
_nebari/provider/cicd/gitlab.py
_nebari/provider/cicd/linter.py
_nebari/provider/cloud/__init__.py
_nebari/provider/cloud/amazon_web_services.py
_nebari/provider/cloud/azure_cloud.py
_nebari/provider/cloud/commons.py
_nebari/provider/cloud/google_cloud.py
_nebari/provider/dns/__init__.py
_nebari/provider/dns/cloudflare.py
_nebari/provider/oauth/__init__.py
_nebari/provider/oauth/auth0.py
_nebari/stages/__init__.py
_nebari/stages/base.py
_nebari/stages/tf_objects.py
_nebari/stages/bootstrap/__init__.py
_nebari/stages/infrastructure/__init__.py
_nebari/stages/infrastructure/template/aws/locals.tf
_nebari/stages/infrastructure/template/aws/main.tf
_nebari/stages/infrastructure/template/aws/outputs.tf
_nebari/stages/infrastructure/template/aws/variables.tf
_nebari/stages/infrastructure/template/aws/versions.tf
_nebari/stages/infrastructure/template/aws/modules/accounting/main.tf
_nebari/stages/infrastructure/template/aws/modules/accounting/variables.tf
_nebari/stages/infrastructure/template/aws/modules/efs/main.tf
_nebari/stages/infrastructure/template/aws/modules/efs/outputs.tf
_nebari/stages/infrastructure/template/aws/modules/efs/variables.tf
_nebari/stages/infrastructure/template/aws/modules/kubernetes/autoscaling.tf
_nebari/stages/infrastructure/template/aws/modules/kubernetes/locals.tf
_nebari/stages/infrastructure/template/aws/modules/kubernetes/main.tf
nebari-2025.10.1.dist-info/METADATA
nebari-2025.10.1.dist-info/WHEEL
nebari-2025.10.1.dist-info/entry_points.txt
nebari-2025.10.1.dist-info/licenses/LICENSE
nebari-2025.10.1.dist-info/RECORD
