Metadata-Version: 2.4
Name: nebari
Version: 2025.10.1
Summary: A Jupyter and Dask-powered open source data science platform.
Project-URL: Documentation, https://www.nebari.dev/docs/welcome
Project-URL: Source, https://github.com/nebari-dev/nebari
Author-email: Nebari development team <internal-it@quansight.com>
License-Expression: BSD-3-Clause
License-File: LICENSE
Keywords: aws,azure,dask,do,gcp,jupyter,nebari
Classifier: Development Status :: 5 - Production/Stable
Classifier: Framework :: Jupyter :: JupyterLab
Classifier: Intended Audience :: Developers
Classifier: Intended Audience :: Education
Classifier: Intended Audience :: Information Technology
Classifier: Intended Audience :: Science/Research
Classifier: Intended Audience :: System Administrators
Classifier: Programming Language :: Python :: 3
Classifier: Programming Language :: Python :: 3.10
Classifier: Programming Language :: Python :: 3.11
Classifier: Programming Language :: Python :: 3.12
Classifier: Programming Language :: Python :: 3.13
Classifier: Topic :: Software Development :: Build Tools
Requires-Python: >=3.10
Requires-Dist: auth0-python==4.7.1
Requires-Dist: azure-identity==1.16.1
Requires-Dist: azure-mgmt-containerservice==26.0.0
Requires-Dist: azure-mgmt-resource==23.0.1
Requires-Dist: bcrypt==4.0.1
Requires-Dist: boto3==1.34.63
Requires-Dist: click<8.2.0
Requires-Dist: cloudflare==2.11.7
Requires-Dist: google-auth<3.0.0,>=2.31.0
Requires-Dist: google-cloud-compute==1.19.1
Requires-Dist: google-cloud-container==2.49.0
Requires-Dist: google-cloud-iam==2.15.1
Requires-Dist: google-cloud-storage==2.18.0
Requires-Dist: grpc-google-iam-v1==0.13.1
Requires-Dist: jinja2
Requires-Dist: kubernetes==27.2.0
Requires-Dist: packaging==23.2
Requires-Dist: pluggy==1.3.0
Requires-Dist: prompt-toolkit==3.0.36
Requires-Dist: pydantic<3.0.0,>=2.9.2
Requires-Dist: pynacl==1.5.0
Requires-Dist: python-keycloak<4.0.0,>=3.9.0
Requires-Dist: questionary==2.0.0
Requires-Dist: requests-toolbelt==1.0.0
Requires-Dist: rich<14,>=13.5.1
Requires-Dist: ruamel-yaml==0.18.6
Requires-Dist: typer==0.9.0
Requires-Dist: typing-extensions>=4.11.0
Provides-Extra: dev
Requires-Dist: black==22.3.0; extra == 'dev'
Requires-Dist: coverage[toml]; extra == 'dev'
Requires-Dist: dask-gateway; extra == 'dev'
Requires-Dist: escapism; extra == 'dev'
Requires-Dist: mypy==1.6.1; extra == 'dev'
Requires-Dist: paramiko; extra == 'dev'
Requires-Dist: pre-commit; extra == 'dev'
Requires-Dist: pytest; extra == 'dev'
Requires-Dist: pytest-cov; extra == 'dev'
Requires-Dist: pytest-playwright; extra == 'dev'
Requires-Dist: pytest-timeout; extra == 'dev'
Requires-Dist: python-dotenv; extra == 'dev'
Requires-Dist: python-hcl2; extra == 'dev'
Requires-Dist: setuptools==63.4.3; extra == 'dev'
Requires-Dist: tqdm; extra == 'dev'
Provides-Extra: docs
Requires-Dist: sphinx; extra == 'docs'
Requires-Dist: sphinx-click; extra == 'docs'
